pyiron_base/__init__.py
pyiron_base/_tests.py
pyiron_base/_version.py
pyiron_base/cli/__init__.py
pyiron_base/cli/__main__.py
pyiron_base/cli/control.py
pyiron_base/cli/cp.py
pyiron_base/cli/install.py
pyiron_base/cli/ls.py
pyiron_base/cli/mv.py
pyiron_base/cli/reloadfile.py
pyiron_base/cli/rm.py
pyiron_base/cli/wrapper.py
pyiron_base/database/__init__.py
pyiron_base/database/filetable.py
pyiron_base/database/generic.py
pyiron_base/database/interface.py
pyiron_base/database/jobtable.py
pyiron_base/database/manager.py
pyiron_base/database/sqlcolumnlength.py
pyiron_base/database/tables.py
pyiron_base/interfaces/__init__.py
pyiron_base/interfaces/factory.py
pyiron_base/interfaces/has_dict.py
pyiron_base/interfaces/has_groups.py
pyiron_base/interfaces/has_hdf.py
pyiron_base/interfaces/lockable.py
pyiron_base/interfaces/object.py
pyiron_base/jobs/__init__.py
pyiron_base/jobs/datamining.py
pyiron_base/jobs/dynamic.py
pyiron_base/jobs/script.py
pyiron_base/jobs/worker.py
pyiron_base/jobs/flex/__init__.py
pyiron_base/jobs/flex/executablecontainer.py
pyiron_base/jobs/flex/factory.py
pyiron_base/jobs/flex/pythonfunctioncontainer.py
pyiron_base/jobs/job/__init__.py
pyiron_base/jobs/job/base.py
pyiron_base/jobs/job/factory.py
pyiron_base/jobs/job/generic.py
pyiron_base/jobs/job/interactive.py
pyiron_base/jobs/job/jobtype.py
pyiron_base/jobs/job/path.py
pyiron_base/jobs/job/runfunction.py
pyiron_base/jobs/job/template.py
pyiron_base/jobs/job/toolkit.py
pyiron_base/jobs/job/util.py
pyiron_base/jobs/job/wrapper.py
pyiron_base/jobs/job/extension/__init__.py
pyiron_base/jobs/job/extension/executable.py
pyiron_base/jobs/job/extension/files.py
pyiron_base/jobs/job/extension/jobstatus.py
pyiron_base/jobs/job/extension/server/__init__.py
pyiron_base/jobs/job/extension/server/generic.py
pyiron_base/jobs/job/extension/server/queuestatus.py
pyiron_base/jobs/job/extension/server/runmode.py
pyiron_base/jobs/master/__init__.py
pyiron_base/jobs/master/flexible.py
pyiron_base-0.15.12.dist-info/METADATA
pyiron_base-0.15.12.dist-info/WHEEL
pyiron_base-0.15.12.dist-info/entry_points.txt
pyiron_base-0.15.12.dist-info/licenses/LICENSE
pyiron_base-0.15.12.dist-info/RECORD
