Metadata-Version: 2.4
Name: pyiron_base
Version: 0.15.12
Summary: Core components of the pyiron integrated development environment (IDE) for computational materials science
Project-URL: Homepage, https://github.com/pyiron/pyiron_base
Project-URL: Documentation, https://github.com/pyiron/pyiron_base
Project-URL: Repository, https://github.com/pyiron/pyiron_base
Author-email: "Max-Planck-Institut für Eisenforschung GmbH - Computational Materials Design (CM) Department" <pyiron@mpie.de>
License: BSD 3-Clause License
License-File: LICENSE
Keywords: pyiron
Classifier: Development Status :: 5 - Production/Stable
Classifier: Intended Audience :: Science/Research
Classifier: License :: OSI Approved :: BSD License
Classifier: Operating System :: OS Independent
Classifier: Programming Language :: Python :: 3.11
Classifier: Programming Language :: Python :: 3.12
Classifier: Programming Language :: Python :: 3.13
Classifier: Topic :: Scientific/Engineering :: Physics
Requires-Python: <3.14,>=3.9
Requires-Dist: cloudpickle<=3.1.2,>=2.2.1
Requires-Dist: executorlib<=1.7.4,>=0.1.0
Requires-Dist: h5io-browser<=0.2.8,>=0.0.14
Requires-Dist: h5py<=3.15.1,>=3.11.0
Requires-Dist: monty<=2025.3.3,>=2025.1.3
Requires-Dist: numpy<=2.4.0,>=1.26.0
Requires-Dist: pandas<=2.3.3,>=2.0.0
Requires-Dist: psutil<=7.2.1,>=5.9.3
Requires-Dist: pyfileindex<=0.1.2,>=0.0.16
Requires-Dist: pyiron-dataclasses<=0.0.9,>=0.0.4
Requires-Dist: pyiron-snippets<=1.0.2,>=1.0.1
Requires-Dist: pysqa<=0.3.3,>=0.1.12
Requires-Dist: sqlalchemy<=2.0.45,>=2.0.22
Requires-Dist: tables==3.10.2
Requires-Dist: tqdm<=4.67.1,>=4.44.0
Requires-Dist: traitlets<=5.14.3,>=5.1.1
Provides-Extra: conda
Requires-Dist: conda-subprocess==0.0.10; extra == 'conda'
Requires-Dist: conda==25.9.1; extra == 'conda'
Provides-Extra: devel
Requires-Dist: gitpython<=3.1.46,>=3.1.23; extra == 'devel'
Provides-Extra: flux
Requires-Dist: jinja2<=3.1.6,>=3.0.0; extra == 'flux'
Provides-Extra: stats
Requires-Dist: pint<=0.25.2,>=0.25; extra == 'stats'
